[{
  "_id": {
    "$oid": "6a230b29b79aca25cb4b58e9"
  },
  "name": "iphone Amazon",
  "price": 499
},
{
  "_id": {
    "$oid": "6a231336b79aca25cb4b58ea"
  },
  "name": "iphone Amazon",
  "price": 499
},
{
  "_id": {
    "$oid": "6a231564bed6fb0a7fade39e"
  },
  "name": "iphone Amazon",
  "price": 499
},
{
  "_id": {
    "$oid": "6a23156abed6fb0a7fade39f"
  },
  "name": "iphone Flipkart",
  "price": 450
},
{
  "_id": {
    "$oid": "6a231b072624c2eca5388528"
  },
  "username": "laxmi",
  "name": "iphone Nykaa",
  "price": 470
},
{
  "_id": {
    "$oid": "6a231bcf2624c2eca5388529"
  },
  "username": "laxmi",
  "name": "iphone Amazon",
  "price": 499
},
{
  "_id": {
    "$oid": "6a231c792624c2eca538852a"
  },
  "username": "laxmi",
  "name": "iphone Flipkart",
  "price": 450
},
{
  "_id": {
    "$oid": "6a2320492624c2eca538852b"
  },
  "username": "laxmi",
  "name": "iphone Amazon",
  "price": 499
},
{
  "_id": {
    "$oid": "6a242f345b5dd3d39be69695"
  },
  "username": "laxmi",
  "name": "Maybelline Serum Matte Lipstick - 8Hr hydration, One-Swipe B...",
  "price": 599
},
{
  "_id": {
    "$oid": "6a24596e1b985f8463c6500e"
  },
  "username": "laxmi",
  "name": "MARS Candylicious Colored Lip Gloss",
  "price": 249
},
{
  "_id": {
    "$oid": "6a29af278e20f3084c0c514b"
  },
  "username": "laxmi",
  "name": "BOLDFIT Shaker Bottle Gym Bottle with Blender Gym Shake...",
  "price": 130
},
{
  "_id": {
    "$oid": "6a29af308e20f3084c0c514c"
  },
  "username": "laxmi",
  "name": "BOLDFIT Shaker Bottle Gym Bottle with Blender Gym Shake...",
  "price": 130
},
{
  "_id": {
    "$oid": "6a29b1088e20f3084c0c514e"
  },
  "username": "laxmi",
  "name": "CROCS",
  "price": 2097
}]